LICENSE
MANIFEST.in
README.md
setup.py
captchanet/__init__.py
captchanet/_version.py
captchanet/callbacks.py
captchanet/captcha_generator.py
captchanet/data.py
captchanet/model.py
captchanet/tqdm_callback.py
captchanet.egg-info/PKG-INFO
captchanet.egg-info/SOURCES.txt
captchanet.egg-info/dependency_links.txt
captchanet.egg-info/top_level.txt
captchanet/fonts/NimbusSanL-Bol.otf
captchanet/fonts/NimbusSanL-Reg.otf
captchanet/utils/__init__.py
captchanet/utils/parallel.py